setup.py
hieratic_dynamodb/__init__.py
hieratic_dynamodb/context.py
hieratic_dynamodb.egg-info/PKG-INFO
hieratic_dynamodb.egg-info/SOURCES.txt
hieratic_dynamodb.egg-info/dependency_links.txt
hieratic_dynamodb.egg-info/entry_points.txt
hieratic_dynamodb.egg-info/requires.txt
hieratic_dynamodb.egg-info/top_level.txt