Metadata-Version: 1.1
Name: hieratic-dynamodb
Version: 0.0.3
Summary: dynamodb plugin for hieratic.
Home-page: https://github.com/succhiello/hieratic-dynamodb
Author: Satoshi Ebihara
Author-email: succhiello@gmail.com
License: MIT
Platform: UNKNOWN
Classifier: Development Status :: 3 - Alpha
Classifier: Environment :: Web Environment
Classifier: Intended Audience :: Developers
Classifier: License :: OSI Approved :: MIT License
Classifier: Operating System :: POSIX :: Linux
Classifier: Programming Language :: Python
